Metadata-Version: 1.1
Name: chattyraspi
Version: 0.0.7
Summary: Allows interaction between Alexa and your Raspberry Pi
Home-page: https://github.com/fcracker79/alexa-home-skill/clients/generic
Author: fcracker79
Author-email: fcracker79@gmail.com
License: MIT
Keywords: alexa alexa-home alexa-skill
Platform: UNKNOWN
Classifier: Development Status :: 4 - Beta
Classifier: Intended Audience :: Developers
Classifier: Topic :: Software Development
Classifier: License :: OSI Approved :: MIT License
Classifier: Programming Language :: Python :: 3.5
